bayes_econ/__init__.py
bayes_econ/foo.py
bayes_econ-0.0.1.dist-info/METADATA
bayes_econ-0.0.1.dist-info/WHEEL
bayes_econ-0.0.1.dist-info/licenses/LICENSE
bayes_econ-0.0.1.dist-info/RECORD
