Metadata-Version: 2.4
Name: bayes-econ
Version: 0.0.1
Summary: A Python package for Bayesian economic analysis
Project-URL: Homepage, https://thomaspinder.github.io/bayes-econ/
Project-URL: Repository, https://github.com/thomaspinder/bayes-econ
Project-URL: Documentation, https://thomaspinder.github.io/bayes-econ/
Author-email: Thomas Pinder <tompinder@live.co.uk>
License-File: LICENSE
Keywords: python
Classifier: Intended Audience :: Developers
Classifier: Programming Language :: Python
Classifier: Programming Language :: Python :: 3
Classifier: Programming Language :: Python :: 3.10
Classifier: Programming Language :: Python :: 3.11
Classifier: Programming Language :: Python :: 3.12
Classifier: Programming Language :: Python :: 3.13
Classifier: Topic :: Software Development :: Libraries :: Python Modules
Requires-Python: <4.0,>=3.10
Requires-Dist: arviz>=0.21.0
Requires-Dist: jax>=0.5.3
Requires-Dist: jaxlib>=0.5.3
Requires-Dist: matplotlib>=3.10.1
Requires-Dist: numpy>=2.2.4
Requires-Dist: numpyro>=0.18.0
Requires-Dist: optax>=0.2.4
Requires-Dist: pandas>=2.2.3
Requires-Dist: polars>=1.27.0
